risc_pipeline/data_mem.v
`timescale 1ns/1ps
module data_mem(
    input  wire [31:0] addr,
    input  wire [31:0] wd,
    input  wire        mem_write,
    output wire [31:0] rd,
    input  wire        clk
);
    reg [31:0] memory [0:255];

    integer i;
    initial begin
        for (i=0; i<256; i=i+1) memory[i] = 32'd0;
    end

    // word addressed
    assign rd = memory[addr[31:2]];

    always @(posedge clk) begin
        if (mem_write)
            memory[addr[31:2]] <= wd;
    end
endmodule

risc_pipeline/alu.v
`timescale 1ns/1ps
module alu(
    input  wire [31:0] a,
    input  wire [31:0] b,
    input  wire [2:0]  alu_ctrl,
    output reg  [31:0] y
);
    always @(*) begin
        case (alu_ctrl)
            3'd0: y = a + b; // ADD
            3'd1: y = a - b; // SUB
            default: y = 32'd0;
        endcase
    end
endmodule

risc_pipeline/reg_file.v
`timescale 1ns/1ps
module reg_file(
    input  wire [4:0]  rs,
    input  wire [4:0]  rt,
    input  wire [4:0]  rd,
    input  wire [31:0] wd,
    input  wire        reg_write,
    output wire [31:0] rd1,
    output wire [31:0] rd2,
    input  wire        clk
);
    reg [31:0] regs [0:31];

    // Optional: init all to 0
    integer i;
    initial begin
        for (i=0; i<32; i=i+1) regs[i] = 32'd0;
    end

    // Read (combinational)
    assign rd1 = (rs == 0) ? 32'd0 : regs[rs];
    assign rd2 = (rt == 0) ? 32'd0 : regs[rt];

    // Write (sequential)
    always @(posedge clk) begin
        if (reg_write && (rd != 0))
            regs[rd] <= wd;
    end
endmodule

risc_non_pipelined/instr_mem.v
`timescale 1ns/1ps
module instr_mem(
    input  wire [31:0] addr,
    output wire [31:0] instr
);
    reg [31:0] memory [0:255];
    integer i;

    // Small demo program
    // Encoding used here:
    // R-type: [opcode(6)][rs(5)][rt(5)][rd(5)][unused(11)]
    // I-type: [opcode(6)][rs(5)][rt(5)][imm(16)]
    //
    // Opcodes:
    // ADD=0, SUB=1, LW=2, SW=3, ADDI=4
    initial begin
        // Initialize entire memory to NOP (0)
        for (i = 0; i < 256; i = i + 1)
            memory[i] = 32'd0;

        // Program:
        // 0: ADDI r1, r0, 10
        memory[0] = {6'd4, 5'd0, 5'd1, 16'd10};

        // 1: ADDI r2, r0, 20
        memory[1] = {6'd4, 5'd0, 5'd2, 16'd20};

        // 2: ADD  r3, r1, r2  => r3 = 30
        memory[2] = {6'd0, 5'd1, 5'd2, 5'd3, 11'd0};

        // 3: SW r3, 0(r0)  => MEM[0] = 30
        memory[3] = {6'd3, 5'd0, 5'd3, 16'd0};

        // 4: LW r4, 0(r0)  => r4 = 30
        memory[4] = {6'd2, 5'd0, 5'd4, 16'd0};

        // 5: SUB r5, r4, r1 => r5 = 20
        memory[5] = {6'd1, 5'd4, 5'd1, 5'd5, 11'd0};
    end

    // PC is byte-addressed, so divide by 4 for word index
    assign instr = memory[addr[31:2]];

endmodule

risc_non_pipelined/pc.v
`timescale 1ns/1ps
module pc(
    input  wire        clk,
    input  wire        reset,
    input  wire [31:0] pc_next,
    output reg  [31:0] pc
);
    always @(posedge clk) begin
        if (reset)
            pc <= 32'd0;
        else
            pc <= pc_next;
    end
endmodule

risc_non_pipelined/cpu_top.v
`timescale 1ns/1ps
module cpu_top(input clk, input reset);

    // Fetch
    wire [31:0] pc;
    wire [31:0] pc_next;
    wire [31:0] instr;

    assign pc_next = pc + 32'd4;

    pc pc1(
        .clk(clk),
        .reset(reset),
        .pc_next(pc_next),
        .pc(pc)
    );

    instr_mem imem(
        .addr(pc),
        .instr(instr)
    );

    // Decode fields
    wire [5:0] opcode = instr[31:26];
    wire [4:0] rs     = instr[25:21];
    wire [4:0] rt     = instr[20:16];
    wire [4:0] rd     = instr[15:11];
    wire [15:0] imm16  = instr[15:0];
    wire [31:0] imm    = {{16{imm16[15]}}, imm16}; // sign-extend

    // Control signals
    reg        reg_write;
    reg        mem_write;
    reg        mem_to_reg;
    reg        alu_src_imm;
    reg        rd_is_rt;       // for I-type destination
    reg [2:0]  alu_ctrl;

    // Simple control decode
    // Opcodes: ADD=0, SUB=1, LW=2, SW=3, ADDI=4
    always @(*) begin
        // defaults
        reg_write  = 1'b0;
        mem_write  = 1'b0;
        mem_to_reg = 1'b0;
        alu_src_imm= 1'b0;
        rd_is_rt   = 1'b0;
        alu_ctrl   = 3'd0;

        case (opcode)
            6'd0: begin // ADD (R-type)
                reg_write = 1'b1;
                alu_ctrl  = 3'd0;
            end
            6'd1: begin // SUB (R-type)
                reg_write = 1'b1;
                alu_ctrl  = 3'd1;
            end
            6'd2: begin // LW
                reg_write  = 1'b1;
                mem_to_reg = 1'b1;
                alu_src_imm= 1'b1;
                rd_is_rt   = 1'b1; // dest = rt
                alu_ctrl   = 3'd0; // addr = rs + imm
            end
            6'd3: begin // SW
                mem_write  = 1'b1;
                alu_src_imm= 1'b1;
                alu_ctrl   = 3'd0; // addr = rs + imm
            end
            6'd4: begin // ADDI
                reg_write  = 1'b1;
                alu_src_imm= 1'b1;
                rd_is_rt   = 1'b1; // dest = rt
                alu_ctrl   = 3'd0;
            end
            default: begin
                // NOP
            end
        endcase
    end

    // Register file
    wire [31:0] reg_data1, reg_data2;
    wire [4:0]  waddr = (rd_is_rt) ? rt : rd;
    wire [31:0] wdata;

    reg_file rf(
        .rs(rs),
        .rt(rt),
        .rd(waddr),
        .wd(wdata),
        .reg_write(reg_write),
        .rd1(reg_data1),
        .rd2(reg_data2),
        .clk(clk)
    );

    // ALU
    wire [31:0] alu_b = (alu_src_imm) ? imm : reg_data2;
    wire [31:0] alu_out;

    alu alu1(
        .a(reg_data1),
        .b(alu_b),
        .alu_ctrl(alu_ctrl),
        .y(alu_out)
    );

    // Data memory
    wire [31:0] mem_out;

    data_mem dmem(
        .addr(alu_out),
        .wd(reg_data2),
        .mem_write(mem_write),
        .rd(mem_out),
        .clk(clk)
    );

    // Writeback mux
    assign wdata = (mem_to_reg) ? mem_out : alu_out;

endmodule

risc_pipeline/tb_cpu.v
`timescale 1ns/1ps
module tb_cpu;
    reg clk;
    reg reset;

    cpu_top uut(.clk(clk), .reset(reset));

    // 10ns clock
    always #5 clk = ~clk;

    initial begin
        $dumpfile("cpu.vcd");
        $dumpvars(0, tb_cpu);

        clk = 0;
        reset = 1;
        #40;       // hold reset for 4 cycles
        reset = 0;

        #300;      // run
        $finish;
    end
endmodule

risc_non_pipelined/cpu.vcd
$date
	Wed Feb 25 14:27:03 2026
$end
$version
	Icarus Verilog
$end
$timescale
	1ps
$end
$scope module tb_cpu $end
$var reg 1 ! clk $end
$var reg 1 " reset $end
$scope module uut $end
$var wire 1 ! clk $end
$var wire 1 " reset $end
$var wire 32 # wdata [31:0] $end
$var wire 5 $ waddr [4:0] $end
$var wire 5 % rt [4:0] $end
$var wire 5 & rs [4:0] $end
$var wire 32 ' reg_data2 [31:0] $end
$var wire 32 ( reg_data1 [31:0] $end
$var wire 5 ) rd [4:0] $end
$var wire 32 * pc_next [31:0] $end
$var wire 32 + pc [31:0] $end
$var wire 6 , opcode [5:0] $end
$var wire 32 - mem_out [31:0] $end
$var wire 32 . instr [31:0] $end
$var wire 16 / imm16 [15:0] $end
$var wire 32 0 imm [31:0] $end
$var wire 32 1 alu_out [31:0] $end
$var wire 32 2 alu_b [31:0] $end
$var reg 3 3 alu_ctrl [2:0] $end
$var reg 1 4 alu_src_imm $end
$var reg 1 5 mem_to_reg $end
$var reg 1 6 mem_write $end
$var reg 1 7 rd_is_rt $end
$var reg 1 8 reg_write $end
$scope module alu1 $end
$var wire 3 9 alu_ctrl [2:0] $end
$var wire 32 : b [31:0] $end
$var wire 32 ; a [31:0] $end
$var reg 32 < y [31:0] $end
$upscope $end
$scope module dmem $end
$var wire 32 = addr [31:0] $end
$var wire 1 ! clk $end
$var wire 1 6 mem_write $end
$var wire 32 > rd [31:0] $end
$var wire 32 ? wd [31:0] $end
$var integer 32 @ i [31:0] $end
$upscope $end
$scope module imem $end
$var wire 32 A instr [31:0] $end
$var wire 32 B addr [31:0] $end
$var integer 32 C i [31:0] $end
$upscope $end
$scope module pc1 $end
$var wire 1 ! clk $end
$var wire 32 D pc_next [31:0] $end
$var wire 1 " reset $end
$var reg 32 E pc [31:0] $end
$upscope $end
$scope module rf $end
$var wire 1 ! clk $end
$var wire 5 F rd [4:0] $end
$var wire 1 8 reg_write $end
$var wire 5 G rs [4:0] $end
$var wire 5 H rt [4:0] $end
$var wire 32 I wd [31:0] $end
$var wire 32 J rd2 [31:0] $end
$var wire 32 K rd1 [31:0] $end
$var integer 32 L i [31:0] $end
$upscope $end
$upscope $end
$upscope $end
$enddefinitions $end
$comment Show the parameter values. $end
$dumpall
$end
#0
$dumpvars
b100000 L
bx K
bx J
bx I
bx H
bx G
bx F
bx E
bx D
b100000000 C
bx B
bx A
b100000000 @
bx ?
bx >
bx =
bx <
bx ;
bx :
bx 9
x8
x7
x6
x5
x4
bx 3
bx 2
bx 1
bx 0
bx /
bx .
bx -
bx ,
bx +
bx *
bx )
bx (
bx '
bx &
bx %
bx $
bx #
1"
0!
$end
#5000
b0 -
b0 >
b1010 #
b1010 I
b1010 1
b1010 <
b1010 =
b1010 2
b1010 :
b1 $
b1 F
b0 '
b0 ?
b0 J
b0 (
b0 ;
b0 K
b0 3
b0 9
17
14
05
06
18
b1010 0
b1010 /
b0 )
b1 %
b1 H
b0 &
b0 G
b100 ,
b10000000000010000000000001010 .
b10000000000010000000000001010 A
b100 *
b100 D
b0 +
b0 B
b0 E
1!
#10000
0!
#15000
b1010 '
b1010 ?
b1010 J
1!
#20000
0!
#25000
1!
#30000
0!
#35000
1!
#40000
0!
0"
#45000
b10100 #
b10100 I
b10100 1
b10100 <
b10100 =
b10100 2
b10100 :
b10 $
b10 F
b0 '
b0 ?
b0 J
b10100 0
b10100 /
b10 %
b10 H
b10000000000100000000000010100 .
b10000000000100000000000010100 A
b1000 *
b1000 D
b100 +
b100 B
b100 E
1!
#50000
0!
#55000
b11110 #
b11110 I
b11110 1
b11110 <
b11110 =
b11 $
b11 F
b1010 (
b1010 ;
b1010 K
07
04
18
b1100000000000 0
b1100000000000 /
b11 )
b1 &
b1 G
b0 ,
b10100 '
b10100 ?
b10100 J
b1000100001100000000000 .
b1000100001100000000000 A
b1100 *
b1100 D
b1000 +
b1000 B
b1000 E
1!
#60000
0!
#65000
b0 #
b0 I
b0 1
b0 <
b0 =
b0 2
b0 :
b0 $
b0 F
b11110 '
b11110 ?
b11110 J
b0 (
b0 ;
b0 K
14
16
08
b0 0
b0 /
b0 )
b11 %
b11 H
b0 &
b0 G
b11 ,
b1100000000110000000000000000 .
b1100000000110000000000000000 A
b10000 *
b10000 D
b1100 +
b1100 B
b1100 E
1!
#70000
0!
#75000
b100 $
b100 F
b11110 #
b11110 I
b0 '
b0 ?
b0 J
17
15
18
14
06
b100 %
b100 H
b10 ,
b1000000001000000000000000000 .
b1000000001000000000000000000 A
b11110 -
b11110 >
b10100 *
b10100 D
b10000 +
b10000 B
b10000 E
1!
#80000
0!
#85000
b0 -
b0 >
b10100 1
b10100 <
b10100 =
b10100 #
b10100 I
b1010 2
b1010 :
b101 $
b101 F
b11110 (
b11110 ;
b11110 K
b1 3
b1 9
07
04
05
18
b10100000000000 0
b10100000000000 /
b101 )
b1 %
b1 H
b100 &
b100 G
b1 ,
b100100000010010100000000000 .
b100100000010010100000000000 A
b1010 '
b1010 ?
b1010 J
b11000 *
b11000 D
b10100 +
b10100 B
b10100 E
1!
#90000
0!
#95000
b11110 -
b11110 >
b0 #
b0 I
b0 2
b0 :
b0 1
b0 <
b0 =
b0 $
b0 F
b0 '
b0 ?
b0 J
b0 (
b0 ;
b0 K
b0 3
b0 9
18
b0 0
b0 /
b0 )
b0 %
b0 H
b0 &
b0 G
b0 ,
b0 .
b0 A
b11100 *
b11100 D
b11000 +
b11000 B
b11000 E
1!
#100000
0!
#105000
b100000 *
b100000 D
b11100 +
b11100 B
b11100 E
1!
#110000
0!
#115000
b100100 *
b100100 D
b100000 +
b100000 B
b100000 E
1!
#120000
0!
#125000
b101000 *
b101000 D
b100100 +
b100100 B
b100100 E
1!
#130000
0!
#135000
b101100 *
b101100 D
b101000 +
b101000 B
b101000 E
1!
#140000
0!
#145000
b110000 *
b110000 D
b101100 +
b101100 B
b101100 E
1!
#150000
0!
#155000
b110100 *
b110100 D
b110000 +
b110000 B
b110000 E
1!
#160000
0!
#165000
b111000 *
b111000 D
b110100 +
b110100 B
b110100 E
1!
#170000
0!
#175000
b111100 *
b111100 D
b111000 +
b111000 B
b111000 E
1!
#180000
0!
#185000
b1000000 *
b1000000 D
b111100 +
b111100 B
b111100 E
1!
#190000
0!
#195000
b1000100 *
b1000100 D
b1000000 +
b1000000 B
b1000000 E
1!
#200000
0!
#205000
b1001000 *
b1001000 D
b1000100 +
b1000100 B
b1000100 E
1!
#210000
0!
#215000
b1001100 *
b1001100 D
b1001000 +
b1001000 B
b1001000 E
1!
#220000
0!
#225000
b1010000 *
b1010000 D
b1001100 +
b1001100 B
b1001100 E
1!
#230000
0!
#235000
b1010100 *
b1010100 D
b1010000 +
b1010000 B
b1010000 E
1!
#240000
0!
#245000
b1011000 *
b1011000 D
b1010100 +
b1010100 B
b1010100 E
1!
#250000
0!
#255000
b1011100 *
b1011100 D
b1011000 +
b1011000 B
b1011000 E
1!
#260000
0!
#265000
b1100000 *
b1100000 D
b1011100 +
b1011100 B
b1011100 E
1!
#270000
0!
#275000
b1100100 *
b1100100 D
b1100000 +
b1100000 B
b1100000 E
1!
#280000
0!
#285000
b1101000 *
b1101000 D
b1100100 +
b1100100 B
b1100100 E
1!
#290000
0!
#295000
b1101100 *
b1101100 D
b1101000 +
b1101000 B
b1101000 E
1!
#300000
0!
#305000
b1110000 *
b1110000 D
b1101100 +
b1101100 B
b1101100 E
1!
#310000
0!
#315000
b1110100 *
b1110100 D
b1110000 +
b1110000 B
b1110000 E
1!
#320000
0!
#325000
b1111000 *
b1111000 D
b1110100 +
b1110100 B
b1110100 E
1!
#330000
0!
#335000
b1111100 *
b1111100 D
b1111000 +
b1111000 B
b1111000 E
1!
